{
    "description": "",
    "tags": [],
    "size": {
        "height": 400,
        "width": 259
    },
    "objects": [
        {
            "id": 14190678,
            "classId": 20379,
            "description": "",
            "geometryType": "rectangle",
            "labelerLogin": "iw@datasetninja.com",
            "createdAt": "2023-07-06T10:27:09.954Z",
            "updatedAt": "2023-07-06T10:27:09.954Z",
            "tags": [],
            "classTitle": "with_mask",
            "points": {
                "exterior": [
                    [
                        110,
                        70
                    ],
                    [
                        176,
                        140
                    ]
                ],
                "interior": []
            }
        }
    ]
}