{
    "description": "",
    "tags": [],
    "size": {
        "height": 235,
        "width": 400
    },
    "objects": [
        {
            "id": 14192749,
            "classId": 20379,
            "description": "",
            "geometryType": "rectangle",
            "labelerLogin": "iw@datasetninja.com",
            "createdAt": "2023-07-06T10:35:04.774Z",
            "updatedAt": "2023-07-06T10:35:04.774Z",
            "tags": [],
            "classTitle": "with_mask",
            "points": {
                "exterior": [
                    [
                        219,
                        35
                    ],
                    [
                        263,
                        85
                    ]
                ],
                "interior": []
            }
        }
    ]
}