{
    "description": "",
    "tags": [],
    "size": {
        "height": 225,
        "width": 400
    },
    "objects": [
        {
            "id": 14192836,
            "classId": 20379,
            "description": "",
            "geometryType": "rectangle",
            "labelerLogin": "iw@datasetninja.com",
            "createdAt": "2023-07-06T10:35:04.790Z",
            "updatedAt": "2023-07-06T10:35:04.790Z",
            "tags": [],
            "classTitle": "with_mask",
            "points": {
                "exterior": [
                    [
                        43,
                        108
                    ],
                    [
                        107,
                        174
                    ]
                ],
                "interior": []
            }
        },
        {
            "id": 14192835,
            "classId": 20379,
            "description": "",
            "geometryType": "rectangle",
            "labelerLogin": "iw@datasetninja.com",
            "createdAt": "2023-07-06T10:35:04.790Z",
            "updatedAt": "2023-07-06T10:35:04.790Z",
            "tags": [],
            "classTitle": "with_mask",
            "points": {
                "exterior": [
                    [
                        77,
                        53
                    ],
                    [
                        163,
                        140
                    ]
                ],
                "interior": []
            }
        },
        {
            "id": 14192834,
            "classId": 20379,
            "description": "",
            "geometryType": "rectangle",
            "labelerLogin": "iw@datasetninja.com",
            "createdAt": "2023-07-06T10:35:04.789Z",
            "updatedAt": "2023-07-06T10:35:04.789Z",
            "tags": [],
            "classTitle": "with_mask",
            "points": {
                "exterior": [
                    [
                        278,
                        92
                    ],
                    [
                        314,
                        137
                    ]
                ],
                "interior": []
            }
        },
        {
            "id": 14192833,
            "classId": 20379,
            "description": "",
            "geometryType": "rectangle",
            "labelerLogin": "iw@datasetninja.com",
            "createdAt": "2023-07-06T10:35:04.788Z",
            "updatedAt": "2023-07-06T10:35:04.788Z",
            "tags": [],
            "classTitle": "with_mask",
            "points": {
                "exterior": [
                    [
                        381,
                        97
                    ],
                    [
                        392,
                        111
                    ]
                ],
                "interior": []
            }
        }
    ]
}