{
    "description": "",
    "tags": [],
    "size": {
        "height": 267,
        "width": 400
    },
    "objects": [
        {
            "id": 14193511,
            "classId": 20379,
            "description": "",
            "geometryType": "rectangle",
            "labelerLogin": "iw@datasetninja.com",
            "createdAt": "2023-07-06T10:37:12.459Z",
            "updatedAt": "2023-07-06T10:37:12.459Z",
            "tags": [],
            "classTitle": "with_mask",
            "points": {
                "exterior": [
                    [
                        66,
                        99
                    ],
                    [
                        209,
                        235
                    ]
                ],
                "interior": []
            }
        }
    ]
}